odoo/addons/web_disable_export_group/README.rst
odoo/addons/web_disable_export_group/__init__.py
odoo/addons/web_disable_export_group/__manifest__.py
odoo/addons/web_disable_export_group/i18n/es.po
odoo/addons/web_disable_export_group/i18n/fr.po
odoo/addons/web_disable_export_group/i18n/hr.po
odoo/addons/web_disable_export_group/i18n/it.po
odoo/addons/web_disable_export_group/i18n/pt.po
odoo/addons/web_disable_export_group/i18n/web_disable_export_group.pot
odoo/addons/web_disable_export_group/i18n/zh_CN.po
odoo/addons/web_disable_export_group/models/__init__.py
odoo/addons/web_disable_export_group/models/ir_http.py
odoo/addons/web_disable_export_group/models/models.py
odoo/addons/web_disable_export_group/readme/CONFIGURE.md
odoo/addons/web_disable_export_group/readme/CONTRIBUTORS.md
odoo/addons/web_disable_export_group/readme/DESCRIPTION.md
odoo/addons/web_disable_export_group/readme/USAGE.md
odoo/addons/web_disable_export_group/security/groups.xml
odoo/addons/web_disable_export_group/security/ir.model.access.csv
odoo/addons/web_disable_export_group/static/description/icon.png
odoo/addons/web_disable_export_group/static/description/index.html
odoo/addons/web_disable_export_group/static/src/views/list/export_all/export_all.esm.js
odoo/addons/web_disable_export_group/static/tests/tours/web_disable_export_group_tour.esm.js
odoo/addons/web_disable_export_group/tests/__init__.py
odoo/addons/web_disable_export_group/tests/test_tour.py
odoo_addon_web_disable_export_group-18.0.1.0.0.4.dist-info/METADATA
odoo_addon_web_disable_export_group-18.0.1.0.0.4.dist-info/WHEEL
odoo_addon_web_disable_export_group-18.0.1.0.0.4.dist-info/top_level.txt
odoo_addon_web_disable_export_group-18.0.1.0.0.4.dist-info/RECORD
