Metadata-Version: 2.1
Name: odoo-addon-web_disable_export_group
Version: 18.0.1.0.0.4
Requires-Python: >=3.10
Requires-Dist: odoo==18.0.*
Summary: Web Disable Export Group
Home-page: https://github.com/OCA/web
License: AGPL-3
Author: Onestein, Tecnativa, Odoo Community Association (OCA)
Author-email: support@odoo-community.org
Classifier: Programming Language :: Python
Classifier: Framework :: Odoo
Classifier: Framework :: Odoo :: 18.0
Classifier: License :: OSI Approved :: GNU Affero General Public License v3
